[{"idx": 0, "title": "विषय सूची", "url": "chapters/chapter-001.html"}, {"idx": 1, "title": "१. डिजिटलाइजेशनको अर्थ", "url": "chapters/chapter-002.html"}, {"idx": 2, "title": "२. डिजिटल संसारको परिचय", "url": "chapters/chapter-003.html"}, {"idx": 3, "title": "४. डिजिटल साक्षरता: सहस्राब्दीको आवश्यकता", "url": "chapters/chapter-004.html"}, {"idx": 4, "title": "५. टाइपिङ सीप", "url": "chapters/chapter-005.html"}, {"idx": 5, "title": "५.१ किबोर्ड किज र तिनीहरूका कार्यहरू", "url": "chapters/chapter-006.html"}, {"idx": 6, "title": "६. फाइल र फोल्डरहरूसँग काम गर्दै", "url": "chapters/chapter-007.html"}, {"idx": 7, "title": "६.४ लाइब्रेरीहरू", "url": "chapters/chapter-008.html"}, {"idx": 8, "title": "६.५ नयाँ फोल्डरको सिर्जना गर्ने", "url": "chapters/chapter-009.html"}, {"idx": 9, "title": "६.६ नयाँ फाइल सिर्जना गर्ने", "url": "chapters/chapter-010.html"}, {"idx": 10, "title": "६.७ फाइल र फोल्डरहरूको पुनः नामाकरण गर्ने", "url": "chapters/chapter-011.html"}, {"idx": 11, "title": "६.८ फाइलहरू र फोल्डरहरू प्रतिलिपि बनाउने तथा सार्ने", "url": "chapters/chapter-012.html"}, {"idx": 12, "title": "६.९ दायाँ थिचेर फाइलहरूको प्रतिलिपि बनाउने विधि", "url": "chapters/chapter-013.html"}, {"idx": 13, "title": "६.१० फाइलहरू मेटाउने", "url": "chapters/chapter-014.html"}, {"idx": 14, "title": "६.११ कम्प्युटरमा भएका फाइलहरू हटाउने", "url": "chapters/chapter-015.html"}, {"idx": 15, "title": "६.१२ फोल्डर हटाउने", "url": "chapters/chapter-016.html"}, {"idx": 16, "title": "६.१६. सुरक्षित गरिएका ढाँचा/पोर्टेबल डकुमेन्ट फोरमाट (Portable Document Format, PDF) मा बनेका फाइलहरूमा काम गर्ने", "url": "chapters/chapter-017.html"}, {"idx": 17, "title": "६.१६.४ निःशुल्क अनलाइन उपकरण साना पी डि एफ (SmallPDF) प्रयोग गरेर पी डि एफ (PDF) फाइल रिसाइज गर्ने", "url": "chapters/chapter-018.html"}, {"idx": 18, "title": "७. कम्प्युटरमा प्रोग्रामहरू स्थापना रद्द (Uninstall) गर्ने", "url": "chapters/chapter-019.html"}, {"idx": 19, "title": "७.२ कन्ट्रोल प्यानलबाट स्थापना रद्द (Uninstall) गर्नुहोस् (कार्यक्रमहरूको लागि)", "url": "chapters/chapter-020.html"}, {"idx": 20, "title": "८. कम्प्युटरलाई बाह्य डिस्प्लेमा जडान गर्ने", "url": "chapters/chapter-021.html"}, {"idx": 21, "title": "९. सफ्टवेयर विरुद्ध एप्लिकेसन(अनुप्रयोग)", "url": "chapters/chapter-022.html"}, {"idx": 22, "title": "९.२ एप्लिकेसन (अनुप्रयोग)", "url": "chapters/chapter-023.html"}, {"idx": 23, "title": "९.३ कम्प्युटरको लागि निर्दिष्टीकरण", "url": "chapters/chapter-024.html"}, {"idx": 24, "title": "आन्तरिक भण्डारण (Internal Storage):", "url": "chapters/chapter-025.html"}, {"idx": 25, "title": "९.४ कम्प्युटरमा निर्दिष्टीकरणहरू कसरी जाँच गर्ने", "url": "chapters/chapter-026.html"}, {"idx": 26, "title": "१०. इन्टरनेट को शक्ती", "url": "chapters/chapter-027.html"}, {"idx": 27, "title": "१०.१ खोज इन्जिनहरू", "url": "chapters/chapter-028.html"}, {"idx": 28, "title": "१०.२ खोजहरूको लागि गुगल प्रयोग गर्ने", "url": "chapters/chapter-029.html"}, {"idx": 29, "title": "११. इन्टरनेटका प्रयोगहरूको उदाहरणहरू", "url": "chapters/chapter-030.html"}, {"idx": 30, "title": "११.१.१ तपाईंको स्मार्टफोनमा नागरिक एप डाउनलोड र स्थापना गर्ने", "url": "chapters/chapter-031.html"}, {"idx": 31, "title": "११.१.२ नागरिक एपमा दर्ता गर्ने", "url": "chapters/chapter-032.html"}, {"idx": 32, "title": "११.२ ड्राइभिङ लाइसेन्सको लागि अनलाइन आवेदन", "url": "chapters/chapter-033.html"}, {"idx": 33, "title": "Applicant Registration", "url": "chapters/chapter-034.html"}, {"idx": 34, "title": "१२. इन्टरनेटबाट फाइलहरू डाउनलोड र अपलोड गर्नुहोस्", "url": "chapters/chapter-035.html"}, {"idx": 35, "title": "१३. डिजिटल सुरक्षा", "url": "chapters/chapter-036.html"}, {"idx": 36, "title": "२. फायरवाल", "url": "chapters/chapter-037.html"}, {"idx": 37, "title": "३. प्रोक्सीहरू", "url": "chapters/chapter-038.html"}, {"idx": 38, "title": "४. कम्प्युटर भाइरस", "url": "chapters/chapter-039.html"}, {"idx": 39, "title": "५. एन्टिभाइरस", "url": "chapters/chapter-040.html"}, {"idx": 40, "title": "१४. इमेल", "url": "chapters/chapter-041.html"}, {"idx": 41, "title": "१४.१ जिमेल (Gmail)", "url": "chapters/chapter-042.html"}, {"idx": 42, "title": "१४.२ इमेल पठाउने", "url": "chapters/chapter-043.html"}, {"idx": 43, "title": "१४.४ इमेल लेख्नको लागि दिशानिर्देश", "url": "chapters/chapter-044.html"}, {"idx": 44, "title": "१. विषय रेखा", "url": "chapters/chapter-045.html"}, {"idx": 45, "title": "२. सही अभिवादन संग सुरु गर्नुहोस्", "url": "chapters/chapter-046.html"}, {"idx": 46, "title": "३. बडि", "url": "chapters/chapter-047.html"}, {"idx": 47, "title": "१४.६ स्याम इमेलहरू र जिमेलमा रहेको स्याम फोल्डर", "url": "chapters/chapter-048.html"}, {"idx": 48, "title": "१४.७ जिमेलमा रहेको स्याम फोल्डरमा पहुँच", "url": "chapters/chapter-049.html"}, {"idx": 49, "title": "१४.८ जिमेलमा रहेको स्याम इमेल बारे रिपोर्ट गर्ने", "url": "chapters/chapter-050.html"}, {"idx": 50, "title": "१४.९ तपाईंको जिमेलमा व्यावसायिक हस्ताक्षर थप्ने", "url": "chapters/chapter-051.html"}, {"idx": 51, "title": "१५. जुम मार्फत भिडियो सम्मेलन/बैठक", "url": "chapters/chapter-052.html"}, {"idx": 52, "title": "१५.२ अनुसूचित बैठक सुरु गर्न", "url": "chapters/chapter-053.html"}, {"idx": 53, "title": "१५.५ भिडियो साझा गर्नु", "url": "chapters/chapter-054.html"}, {"idx": 54, "title": "१५.६ आफ्नो स्क्रिन साझा गर्नु", "url": "chapters/chapter-055.html"}, {"idx": 55, "title": "१५.७ सहभागीहरूसँग कुराकानी/सन्देश", "url": "chapters/chapter-056.html"}, {"idx": 56, "title": "१५.८ जुम बैठकका नियन्त्रणहरू", "url": "chapters/chapter-057.html"}, {"idx": 57, "title": "१६. माइक्रोसफ्ट अफिसका उपकरणहरू", "url": "chapters/chapter-058.html"}, {"idx": 58, "title": "फाइल ट्याब", "url": "chapters/chapter-059.html"}, {"idx": 59, "title": "१६.१.२ माइक्रोसफ्ट वर्डका विशेषताहरू", "url": "chapters/chapter-060.html"}, {"idx": 60, "title": "व्यावहारिक सत्र", "url": "chapters/chapter-061.html"}, {"idx": 61, "title": "१६.२ स्प्रेडसिट आवेदन", "url": "chapters/chapter-062.html"}, {"idx": 62, "title": "१६.२.२ माइक्रोसफ्ट एक्सेलका विशेषताहरू", "url": "chapters/chapter-063.html"}, {"idx": 63, "title": "१. गणना (COUNT)", "url": "chapters/chapter-064.html"}, {"idx": 64, "title": "२. म्याक्स र मिन (MAX and MIN)", "url": "chapters/chapter-065.html"}, {"idx": 65, "title": "१६.४.१ माइक्रोसफ्ट पावरपोरइन्ट (Microsoft Powerpoint)", "url": "chapters/chapter-066.html"}, {"idx": 66, "title": "१६.४.२ पावरपोरइन्टका विशेषताहरू", "url": "chapters/chapter-067.html"}, {"idx": 67, "title": "व्यावहारिक सत्र", "url": "chapters/chapter-068.html"}, {"idx": 68, "title": "१७. सामाजिक संजाल र यसको परिणामहरू", "url": "chapters/chapter-069.html"}, {"idx": 69, "title": "१७.२ सामाजिक संजाल - एक उप", "url": "chapters/chapter-070.html"}, {"idx": 70, "title": "१७.४ दुई-कारक प्रमाणीकरण र एक-समय/अस्थायी पासकोडहरू", "url": "chapters/chapter-071.html"}, {"idx": 71, "title": "१८. अनलाइन स्रोतहरूको मूल्याङ्कन", "url": "chapters/chapter-072.html"}, {"idx": 72, "title": "१९. लिङ्गडइन (LinkedIn) को परिचय", "url": "chapters/chapter-073.html"}, {"idx": 73, "title": "१९.१ लिङडइनमा सुरु गर्दै हुनुहुन्छ ?", "url": "chapters/chapter-074.html"}, {"idx": 74, "title": "१९.२ लिङडइनमा मानिसहरू खोजी गर्नु", "url": "chapters/chapter-075.html"}, {"idx": 75, "title": "१९.३ मानिसहरूसँग सम्पर्कमा रहनु", "url": "chapters/chapter-076.html"}, {"idx": 76, "title": "२०. साइबर बुलिङ", "url": "chapters/chapter-077.html"}, {"idx": 77, "title": "२०.१ साइबरबुलिजसँग सम्झौता गर्ने", "url": "chapters/chapter-078.html"}, {"idx": 78, "title": "२०.२ के तपाईं साइबरबुली हुनुहुन्छ ?", "url": "chapters/chapter-079.html"}, {"idx": 79, "title": "२१. गुगल वर्कस्पेस Google Workspaceर अनुप्रयोगहरू", "url": "chapters/chapter-080.html"}, {"idx": 80, "title": "२१.१ Google Drive (गुगल ड्राइभ)", "url": "chapters/chapter-081.html"}, {"idx": 81, "title": "Manage versions", "url": "chapters/chapter-082.html"}, {"idx": 82, "title": "नयाँ संस्करण अपलोड गर्नुहोस्", "url": "chapters/chapter-083.html"}, {"idx": 83, "title": "पुरानो संस्करण मेटाउनुहोस्", "url": "chapters/chapter-084.html"}, {"idx": 84, "title": "२१.२ गुगल कागजात, पाना र स्लाइडहरूमा वास्तविक-समय साक्षेपसहयोग", "url": "chapters/chapter-085.html"}, {"idx": 85, "title": "२१.३ गुगल नक्सा", "url": "chapters/chapter-086.html"}, {"idx": 86, "title": "२१.४.६ प्रश्नहरू मेटाउने", "url": "chapters/chapter-087.html"}, {"idx": 87, "title": "२१.४.७ आवश्यक प्रश्नहरू", "url": "chapters/chapter-088.html"}, {"idx": 88, "title": "२१.४.८ रड/विषयवस्तुहरूको निर्माण", "url": "chapters/chapter-089.html"}, {"idx": 89, "title": "२१.४.९ प्रतिक्रियाहरू हेर्ने", "url": "chapters/chapter-090.html"}, {"idx": 90, "title": "२१.५ गुगल क्यालेन्डर", "url": "chapters/chapter-091.html"}, {"idx": 91, "title": "२२. डाटाका आधारभूत कुराहरू", "url": "chapters/chapter-092.html"}, {"idx": 92, "title": "२३. डाटाको वर्गीकरण", "url": "chapters/chapter-093.html"}, {"idx": 93, "title": "२४. डाटा सङ्गलन विधिका प्रकारहरू", "url": "chapters/chapter-094.html"}, {"idx": 94, "title": "२४.१.१ प्रश्नावली को अवयवहरू", "url": "chapters/chapter-095.html"}, {"idx": 95, "title": "२४.१.३ प्रश्नावली सिर्जना गर्न प्रयोग गरिएको मूल्याङ्कन मापदण्डहरू", "url": "chapters/chapter-096.html"}, {"idx": 96, "title": "२४.२ अन्तर्वार्ता", "url": "chapters/chapter-097.html"}, {"idx": 97, "title": "२४.३ अवलोकन", "url": "chapters/chapter-098.html"}, {"idx": 98, "title": "२५. डाटा जीवन चक्र", "url": "chapters/chapter-099.html"}, {"idx": 99, "title": "२६. डाटा साक्षरता सीप र दक्षताहरू", "url": "chapters/chapter-100.html"}, {"idx": 100, "title": "२६.२ डाटा सङ्कलन", "url": "chapters/chapter-101.html"}, {"idx": 101, "title": "२६.३ डाटा भण्डारण", "url": "chapters/chapter-102.html"}, {"idx": 102, "title": "२६.४ डाटा सुरक्षा र व्याकअप/संचय", "url": "chapters/chapter-103.html"}, {"idx": 103, "title": "२६.५ डाटा विश्लेषण", "url": "chapters/chapter-104.html"}, {"idx": 104, "title": "२६.५.२ डाटा क्लिनिङ्ग", "url": "chapters/chapter-105.html"}, {"idx": 105, "title": "२६.५.३ डाटा अन्वेषण", "url": "chapters/chapter-106.html"}, {"idx": 106, "title": "२६.५.४ डाटा रूपान्तरण", "url": "chapters/chapter-107.html"}, {"idx": 107, "title": "२६.५.५ डाटा माडेलिङ", "url": "chapters/chapter-108.html"}, {"idx": 108, "title": "२६.५.६ डाटा व्याख्या", "url": "chapters/chapter-109.html"}, {"idx": 109, "title": "Highest Demand Skill", "url": "chapters/chapter-110.html"}, {"idx": 110, "title": "२७. डाटा विश्लेषण", "url": "chapters/chapter-111.html"}, {"idx": 111, "title": "२७.१.२ आवृत्ति वितरण", "url": "chapters/chapter-112.html"}, {"idx": 112, "title": "२. माध्य(Median)", "url": "chapters/chapter-113.html"}, {"idx": 113, "title": "२७.१.४ परिवर्तनशीलता मापन", "url": "chapters/chapter-114.html"}, {"idx": 114, "title": "१. दायरा(Range)", "url": "chapters/chapter-115.html"}, {"idx": 115, "title": "२. मानक विचलन(Standard Deviation)", "url": "chapters/chapter-116.html"}, {"idx": 116, "title": "२७.२.२ सहसम्बन्ध", "url": "chapters/chapter-117.html"}, {"idx": 117, "title": "२७.२.३ रैखिक प्रतिगमन", "url": "chapters/chapter-118.html"}, {"idx": 118, "title": "२८. डाटा-संचालित अनुसन्धान पद्धति", "url": "chapters/chapter-119.html"}, {"idx": 119, "title": "२८.२ साहित्य समीक्षा", "url": "chapters/chapter-120.html"}, {"idx": 120, "title": "२८.३ अनुसन्धान डिजाइन", "url": "chapters/chapter-121.html"}, {"idx": 121, "title": "२८.४ डाटा सङ्गलन", "url": "chapters/chapter-122.html"}, {"idx": 122, "title": "२८.५ नमूना", "url": "chapters/chapter-123.html"}, {"idx": 123, "title": "२. व्यवस्थित नमूना", "url": "chapters/chapter-124.html"}, {"idx": 124, "title": "३. स्तरीकृत नमूना", "url": "chapters/chapter-125.html"}, {"idx": 125, "title": "२८.५.२ गैर-सम्भाव्यता नमूना", "url": "chapters/chapter-126.html"}, {"idx": 126, "title": "२८.६ डाटा विश्लेषण", "url": "chapters/chapter-127.html"}, {"idx": 127, "title": "२८.७ सिफारिस र निर्णय गर्ने", "url": "chapters/chapter-128.html"}]